managed_service_fixtures/__init__.py
managed_service_fixtures/base_manager.py
managed_service_fixtures/run_service_executor.py
managed_service_fixtures/services/__init__.py
managed_service_fixtures/services/asgi_app.py
managed_service_fixtures/services/cockroach.py
managed_service_fixtures/services/moto.py
managed_service_fixtures/services/redis.py
managed_service_fixtures/services/vault.py
managed_service_fixtures-0.3.1.dist-info/LICENSE
managed_service_fixtures-0.3.1.dist-info/METADATA
managed_service_fixtures-0.3.1.dist-info/WHEEL
managed_service_fixtures-0.3.1.dist-info/RECORD
