Metadata-Version: 2.1
Name: managed_service_fixtures
Version: 0.3.1
Summary: Pytest fixtures to manage external services such as Cockroach DB, Vault, or Redis
Home-page: https://github.com/noteable-io/managed-service-fixtures
License: BSD-3
Keywords: pytest
Author: Noteable Engineering
Author-email: engineering-backend@noteable.io
Requires-Python: >=3.8,<4.0
Classifier: License :: Other/Proprietary License
Classifier: Programming Language :: Python :: 3
Classifier: Programming Language :: Python :: 3.8
Classifier: Programming Language :: Python :: 3.9
Classifier: Programming Language :: Python :: 3.10
Classifier: Programming Language :: Python :: 3.11
Requires-Dist: click (>=8.1.3,<9.0.0)
Requires-Dist: filelock (>=3.7.1,<4.0.0)
Requires-Dist: importlib-metadata (>=4.12.0,<5.0.0)
Requires-Dist: mirakuru (>=2.4.2,<3.0.0)
Requires-Dist: pytest (>=7.1.0,<8.0.0)
Requires-Dist: pytest-asyncio
Requires-Dist: pytest-xdist
Project-URL: Repository, https://github.com/noteable-io/managed-service-fixtures
